.gitignore
LICENCE.txt
MANIFEST.in
Makefile
README.md
requirements.txt
setup.py
.github/workflows/pythonpackage.yml
pandas_jsonlines/__init__.py
pandas_jsonlines/read_jsonlines.py
pandas_jsonlines.egg-info/PKG-INFO
pandas_jsonlines.egg-info/SOURCES.txt
pandas_jsonlines.egg-info/dependency_links.txt
pandas_jsonlines.egg-info/not-zip-safe
pandas_jsonlines.egg-info/requires.txt
pandas_jsonlines.egg-info/top_level.txt
tests/__init__.py
tests/test_rjsl.py
tests/data/data.jsonlines